jikanpy/__init__.py
jikanpy/aiojikan.py
jikanpy/exceptions.py
jikanpy/jikan.py
jikanpy/py.typed
jikanpy/utils.py
jikanpy_v4-1.0.2.dist-info/LICENSE
jikanpy_v4-1.0.2.dist-info/METADATA
jikanpy_v4-1.0.2.dist-info/WHEEL
jikanpy_v4-1.0.2.dist-info/top_level.txt
jikanpy_v4-1.0.2.dist-info/RECORD
