Metadata-Version: 2.1
Name: jikanpy-v4
Version: 1.0.2
Summary: Python wrapper for the Jikan API
Home-page: https://github.com/abhinavk99/jikanpy
Author: Chris Peterson
Author-email: chris.peterson444@gmail.com
License: MIT
Keywords: jikan,jikanpy,api,myanimelist
Classifier: Programming Language :: Python :: 3
Classifier: Programming Language :: Python :: 3.6
Classifier: Programming Language :: Python :: 3.7
Classifier: License :: OSI Approved :: MIT License
Requires-Python: >=3.6
License-File: LICENSE
